README
setup.py
gevent_dht/__init__.py
gevent_dht/api.py
gevent_dht/finger.py
gevent_dht/network.py
gevent_dht/node.py
gevent_dht/protocol.py
gevent_dht/set_store.py
gevent_dht/uidlib.py
gevent_dht.egg-info/PKG-INFO
gevent_dht.egg-info/SOURCES.txt
gevent_dht.egg-info/dependency_links.txt
gevent_dht.egg-info/requires.txt
gevent_dht.egg-info/top_level.txt