Metadata-Version: 1.0
Name: gevent-dht
Version: 0.1.1
Summary: Gevent based distributed hash table
Home-page: github.com/c00w/gevent_dht
Author: Colin Rice
Author-email: dah4k0r@gmail.com
License: MIT Expat License
Platform: UNKNOWN
Classifier: Development Status :: 4 - Beta
Classifier: Intended Audience :: Developers
Classifier: Topic :: System :: Networking
Classifier: License :: OSI Approved :: MIT License
